fluidgym/__init__.py
fluidgym/config.py
fluidgym/py.typed
fluidgym/registry.py
fluidgym/types.py
fluidgym/envs/__init__.py
fluidgym/envs/fluid_env.py
fluidgym/envs/parallel_env.py
fluidgym/envs/airfoil/__init__.py
fluidgym/envs/airfoil/airfoil_env_2d.py
fluidgym/envs/airfoil/airfoil_env_3d.py
fluidgym/envs/airfoil/airfoil_env_base.py
fluidgym/envs/airfoil/coords.py
fluidgym/envs/airfoil/grid.py
fluidgym/envs/cylinder/__init__.py
fluidgym/envs/cylinder/cylinder_env_base.py
fluidgym/envs/cylinder/grid.py
fluidgym/envs/cylinder/jet_cylinder_env_2d.py
fluidgym/envs/cylinder/jet_cylinder_env_3d.py
fluidgym/envs/cylinder/rotating_cylinder_env_2d.py
fluidgym/envs/rbc/__init__.py
fluidgym/envs/rbc/rbc_env_2d.py
fluidgym/envs/rbc/rbc_env_3d.py
fluidgym/envs/rbc/rbc_env_base.py
fluidgym/envs/tcf/__init__.py
fluidgym/envs/tcf/grid.py
fluidgym/envs/tcf/tcf_env.py
fluidgym/envs/util/__init__.py
fluidgym/envs/util/forces.py
fluidgym/envs/util/obs_extraction.py
fluidgym/envs/util/profiles.py
fluidgym/envs/util/visualization.py
fluidgym/integration/__init__.py
fluidgym/integration/gymnasium.py
fluidgym/integration/pettingzoo.py
fluidgym/integration/torchrl.py
fluidgym/integration/sb3/__init__.py
fluidgym/integration/sb3/eval_callback.py
fluidgym/integration/sb3/util.py
fluidgym/integration/sb3/vec_env.py
fluidgym/simulation/__init__.py
fluidgym/simulation/helpers.py
fluidgym/simulation/simulation.py
fluidgym/simulation/extensions/PISO_multiblock_cuda_kernel.cu
fluidgym/simulation/extensions/PISOtorch.cpp
fluidgym/simulation/extensions/PISOtorch.cpython-312-x86_64-linux-gnu.so
fluidgym/simulation/extensions/__init__.py
fluidgym/simulation/extensions/bicgstab_solver_kernel.cu
fluidgym/simulation/extensions/cg_solver_kernel.cu
fluidgym/simulation/extensions/domain_structs.cpp
fluidgym/simulation/extensions/eigenvalue.cu
fluidgym/simulation/extensions/grid_gen.cu
fluidgym/simulation/extensions/matrix_vector_ops.cu
fluidgym-0.1.0.dist-info/METADATA
fluidgym-0.1.0.dist-info/WHEEL
fluidgym-0.1.0.dist-info/top_level.txt
fluidgym-0.1.0.dist-info/RECORD
fluidgym-0.1.0.dist-info/licenses/LICENSE
fluidgym-0.1.0.dist-info/licenses/LICENSES/Apache-2.0.txt
fluidgym-0.1.0.dist-info/sboms/auditwheel.cdx.json
