Metadata-Version: 2.4
Name: fluidgym
Version: 0.1.0
Summary: Plug-and-Play Benchmarking of Reinforcement Learning Algorithms for Large-Scale Flow Control
Author-email: Jannis Becktepe <jannis.becktepe@tu-dortmund.de>
License: MIT License
Classifier: Development Status :: 3 - Alpha
Classifier: Intended Audience :: Science/Research
Classifier: Programming Language :: Python :: 3.10
Classifier: Programming Language :: Python :: 3.11
Classifier: Programming Language :: Python :: 3.12
Classifier: Programming Language :: Python :: 3.13
Requires-Python: <3.14,>=3.10
License-File: LICENSE
License-File: LICENSES/Apache-2.0.txt
Requires-Dist: torch==2.9.*
Requires-Dist: gymnasium
Requires-Dist: numpy
Requires-Dist: pandas
Requires-Dist: matplotlib<3.10,>=3.9
Requires-Dist: seaborn
Requires-Dist: huggingface_hub>=1.0.0
Requires-Dist: scikit-image
Requires-Dist: imageio
Requires-Dist: platformdirs
Provides-Extra: dev
Requires-Dist: pre-commit; extra == "dev"
Requires-Dist: ruff; extra == "dev"
Requires-Dist: mypy; extra == "dev"
Requires-Dist: pytest; extra == "dev"
Requires-Dist: types-seaborn; extra == "dev"
Requires-Dist: pandas-stubs; extra == "dev"
Requires-Dist: types-setuptools; extra == "dev"
Requires-Dist: scipy-stubs; extra == "dev"
Provides-Extra: docs
Requires-Dist: sphinx; extra == "docs"
Requires-Dist: sphinx-rtd-theme; extra == "docs"
Provides-Extra: experiments
Requires-Dist: hydra-core; extra == "experiments"
Requires-Dist: gymnasium==1.2.1; extra == "experiments"
Requires-Dist: numpy==2.2.6; extra == "experiments"
Requires-Dist: pandas==2.3.2; extra == "experiments"
Requires-Dist: matplotlib==3.9.4; extra == "experiments"
Requires-Dist: seaborn==0.13.2; extra == "experiments"
Requires-Dist: wandb; extra == "experiments"
Requires-Dist: stable-baselines3[extra]==2.7.0; extra == "experiments"
Requires-Dist: rliable; extra == "experiments"
Provides-Extra: sb3
Requires-Dist: gymnasium>=1.2.1; extra == "sb3"
Requires-Dist: stable-baselines3[extra]>=2.7.0; extra == "sb3"
Provides-Extra: torchrl
Requires-Dist: gymnasium>=1.2.1; extra == "torchrl"
Requires-Dist: torchrl; extra == "torchrl"
Provides-Extra: pettingzoo
Requires-Dist: gymnasium>=1.2.1; extra == "pettingzoo"
Requires-Dist: pettingzoo; extra == "pettingzoo"
Dynamic: license-file
